.gitignore
LICENSE
MANIFEST.in
README.md
pyproject.toml
requirements.txt
setup.cfg
setup.py
.github/workflows/gh_pages.yml
.github/workflows/release.yml
autonomy_toolkit/__init__.py
autonomy_toolkit/_atk_base.py
autonomy_toolkit/_version.py
autonomy_toolkit/db.py
autonomy_toolkit/dev.py
autonomy_toolkit/docker/default-compose.yml
autonomy_toolkit/docker/dockerignore
autonomy_toolkit/docker/dev/dev.dockerfile
autonomy_toolkit/docker/vnc/vnc.dockerfile
autonomy_toolkit/ros/__init__.py
autonomy_toolkit/ros/messages.py
autonomy_toolkit/utils/__init__.py
autonomy_toolkit/utils/docker.py
autonomy_toolkit/utils/files.py
autonomy_toolkit/utils/logger.py
autonomy_toolkit/utils/yaml_parser.py
avtoolbox.egg-info/PKG-INFO
avtoolbox.egg-info/SOURCES.txt
avtoolbox.egg-info/dependency_links.txt
avtoolbox.egg-info/entry_points.txt
avtoolbox.egg-info/requires.txt
avtoolbox.egg-info/top_level.txt
tutorials/using-the-development-environment/README.md