Metadata-Version: 2.1
Name: avtoolbox
Version: 0.0.42
Summary: Autonomy Toolkit
Home-page: https://projects.sbel.org/autonomy-toolkit
Author: UW Simulation Based Engineering Lab
License: BSD3
Project-URL: Homepage, https://projects.sbel.org/autonomy-toolkit
Project-URL: Bug Reports, https://github.com/uwsbel/autonomy-toolkit/issues
Project-URL: Source Code, https://github.com/uwsbel/autonomy-toolkit/
Project-URL: Our Lab!, https://sbel.wisc.edu
Platform: UNKNOWN
Classifier: Development Status :: 3 - Alpha
Classifier: Topic :: Software Development
Classifier: License :: OSI Approved :: MIT License
Classifier: Programming Language :: Python :: 3
Requires-Python: >=3.8.2, <4
License-File: LICENSE
